pycountry_un/__init__.py
pycountry_un/db.py
pycountry_un/load.py
pycountry_un-0.1.1.dist-info/LICENSE
pycountry_un-0.1.1.dist-info/WHEEL
pycountry_un-0.1.1.dist-info/METADATA
pycountry_un-0.1.1.dist-info/RECORD
