Metadata-Version: 2.1
Name: pycountry-un
Version: 0.1.1
Summary: Provide lists in the United Nation's World Economic Situation and Prospects
Home-page: https://github.com/fabiommendes/pycountry_un
License: UNKNOWN
Author: Fábio Macêdo Mendes
Author-email: fabiomacedomendes@gmail.com
Classifier: License :: OSI Approved :: MIT License
Requires-Dist: pycountry~=19.8
Requires-Dist: black ; extra == "dev"
Requires-Dist: twine ; extra == "dev"
Requires-Dist: coverage~=5.0 ; extra == "test"
Requires-Dist: pytest~=5.0 ; extra == "test"
Provides-Extra: dev
Provides-Extra: test
